{"objname": "2016gym", "ra": "21:37:60.00", "redshift": null, "hostname": null, "host_redshift": null, "isTNS_AT": "1", "discoverydate": "2016-10-04 18:01:26", "discoverymag": "19.71", "discmagfilter": "75", "public": "1", "end_prop_period": null, "sourceid": "2", "discovererid": "35587", "name_prefix": "AT", "type": null, "name": null, "discoverer": null, "internal_name": "Gaia16blp", "spectra": [], "dec": "+50:40:59.95", "object_type": {"name": null, "id": null}, "source_group": {"groupid": "24", "group_name": "GaiaAlerts"}}