{"end_prop_period": null, "discoverydate": "2016-12-17 17:28:19", "ra": "22:40:53.98", "dec": "-07:04:27.41", "hostname": null, "name": null, "public": "1", "isTNS_AT": "1", "discovererid": "35587", "objname": "2016jgw", "type": null, "redshift": null, "internal_name": "Gaia17abf", "discoverymag": "16.83", "discmagfilter": "75", "spectra": [], "name_prefix": "AT", "host_redshift": null, "object_type": {"id": null, "name": null}, "source_group": {"group_name": "GaiaAlerts", "groupid": "24"}, "discoverer": null, "sourceid": "2"}