{"objname": "2016gpg", "ra": "23:22:17.68", "redshift": null, "hostname": "UGC12558", "host_redshift": null, "isTNS_AT": "1", "discoverydate": "2016-09-25 22:19:12", "discoverymag": "18.5", "discmagfilter": "1", "public": "1", "end_prop_period": null, "sourceid": "1", "discovererid": "149", "name_prefix": "AT", "type": null, "name": null, "discoverer": "Ciabattari", "internal_name": "", "spectra": [], "dec": "+50:09:20.90", "object_type": {"name": null, "id": null}, "source_group": {"groupid": "27", "group_name": "ISSP"}}