{"objname": "2016hqn", "ra": "23:22:18.90", "redshift": null, "hostname": null, "host_redshift": null, "isTNS_AT": "1", "discoverydate": "2016-10-19 08:58:33", "discoverymag": "20.76", "discmagfilter": "23", "public": "1", "end_prop_period": null, "sourceid": "2", "discovererid": "35588", "name_prefix": "AT", "type": null, "name": null, "discoverer": null, "internal_name": "PS16ewa", "spectra": [], "dec": "+13:03:53.53", "object_type": {"name": null, "id": null}, "source_group": {"groupid": "4", "group_name": "Pan-STARRS1"}}