{
	"dec":"+43:40:34.64",
	"discmagfilter":{
		"family":"PTF",
		"id":"50",
		"name":"R"
	},
	"discoverer":null,
	"discovererid":"11756",
	"discoverydate":"2016-08-15 08:36:57",
	"discoverymag":"19.883",
	"end_prop_period":"2018-08-15",
	"host_redshift":null,
	"hostname":"",
	"internal_name":"iPTF16faw",
	"isTNS_AT":"1",
	"name":"2016faw",
	"name_prefix":"AT",
	"object_type":{
		"id":null,
		"name":null
	},
	"objname":"2016faw",
	"public":"1",
	"ra":"01:17:06.07",
	"redshift":null,
	"source_group":{
		"group_name":"iPTF",
		"groupid":"2"
	},
	"sourceid":"2",
	"spectra":[],
	"type":null
}