{"objname": "2016cyw", "ra": "01:25:56.25", "redshift": null, "hostname": "IC1702", "host_redshift": null, "isTNS_AT": "1", "discoverydate": "2016-07-05 02:12:06", "discoverymag": "17.2", "discmagfilter": "1", "public": "1", "end_prop_period": null, "sourceid": "1", "discovererid": "157", "name_prefix": "SN", "type": "11", "name": "SN IIP", "discoverer": "Briganti", "internal_name": "", "spectra": [], "dec": "+16:35:43.72", "object_type": {"name": null, "id": "11"}, "source_group": {"groupid": "27", "group_name": "ISSP"}}