{"objname": "2016ece", "ra": "02:03:01.80", "redshift": null, "hostname": null, "host_redshift": null, "isTNS_AT": "1", "discoverydate": "2016-05-26 17:29:45", "discoverymag": "18.69", "discmagfilter": "75", "public": "1", "end_prop_period": null, "sourceid": "2", "discovererid": "35587", "name_prefix": "AT", "type": null, "name": null, "discoverer": null, "internal_name": "Gaia16aqs", "spectra": [], "dec": "-11:33:21.30", "object_type": {"name": null, "id": null}, "source_group": {"groupid": "24", "group_name": "GaiaAlerts"}}