{"objname": "2016ggz", "ra": "05:58:45.47", "redshift": null, "hostname": null, "host_redshift": null, "isTNS_AT": "1", "discoverydate": "2016-09-11 13:45:07", "discoverymag": "15.27", "discmagfilter": "75", "public": "1", "end_prop_period": null, "sourceid": "2", "discovererid": "35587", "name_prefix": "AT", "type": null, "name": null, "discoverer": null, "internal_name": "Gaia16bgq", "spectra": [], "dec": "+39:15:33.19", "object_type": {"name": null, "id": null}, "source_group": {"groupid": "24", "group_name": "GaiaAlerts"}}