{"objname": "2016aju", "ra": "08:05:29.42", "redshift": null, "hostname": null, "host_redshift": null, "isTNS_AT": "1", "discoverydate": "2016-01-14 12:10:15", "discoverymag": "21.4384", "discmagfilter": "26", "public": "1", "end_prop_period": null, "sourceid": "1", "discovererid": "49", "name_prefix": "AT", "type": null, "name": null, "discoverer": "Young", "internal_name": "PS16zp", "spectra": [], "dec": "+29:27:53.54", "object_type": {"name": null, "id": null}, "source_group": {"groupid": "4", "group_name": "Pan-STARRS1"}}