{"objname": "2016ibp", "ra": "14:31:27.03", "redshift": null, "hostname": null, "host_redshift": null, "isTNS_AT": "1", "discoverydate": "2016-11-10 00:00:00", "discoverymag": "18.82", "discmagfilter": "75", "public": "1", "end_prop_period": null, "sourceid": "2", "discovererid": "35587", "name_prefix": "AT", "type": null, "name": null, "discoverer": null, "internal_name": "Gaia16btm", "spectra": [], "dec": "+37:14:20.11", "object_type": {"name": null, "id": null}, "source_group": {"groupid": "24", "group_name": "GaiaAlerts"}}