{"end_prop_period": null, "discoverydate": "2017-02-25 11:45:36", "ra": "11:21:39.84", "dec": "-05:38:15.89", "hostname": null, "name": "SN Ia", "public": "1", "isTNS_AT": "1", "discovererid": "35588", "objname": "2017blk", "type": "3", "redshift": "0.0555", "internal_name": "PS17bod", "discoverymag": "18.66", "discmagfilter": "26", "spectra": [{"reducer": "F. Taddia, J. Sollerman, C. Fremling", "remarks": "", "exptime": "900", "jd": 2457820, "public": "1", "obsdate": "2017-03-07 08:30:08", "instrument": {"id": "31", "name": "EFOSC2-NTT"}, "observer": "C. Barbarino, A. Nyholm", "assoc_groups": [{"id": "1", "name": "PESSTO"}], "telescope": {"id": "30", "name": "ESO-NTT"}, "asciifile": "https://wis-tns.weizmann.ac.il/system/files/uploaded//tns_2017blk_2017-03-07_08-30-08_ESO-NTT_EFOSC2-NTT.asci", "source_group": {"id": "1", "name": "PESSTO"}, "end_prop_period": null, "fitsfile": "https://wis-tns.weizmann.ac.il/system/files/uploaded//tns_2017blk_2017-03-07_08-30-08_ESO-NTT_EFOSC2-NTT.fits"}], "name_prefix": "SN", "host_redshift": null, "object_type": {"id": "3", "name": null}, "source_group": {"group_name": "Pan-STARRS1", "groupid": "4"}, "discoverer": null, "sourceid": "2"}