{
	"dec":"+35:22:57.94",
	"discmagfilter":{
		"family":"Gaia",
		"id":"75",
		"name":"G"
	},
	"discoverer":null,
	"discovererid":"35587",
	"discoverydate":"2017-02-11 00:37:26",
	"discoverymag":"18.67",
	"end_prop_period":null,
	"host_redshift":null,
	"hostname":null,
	"internal_name":"Gaia17ajz",
	"isTNS_AT":"1",
	"name":"2017axj",
	"name_prefix":"AT",
	"object_type":{
		"id":null,
		"name":null
	},
	"objname":"2017axj",
	"public":"1",
	"ra":"05:25:11.80",
	"redshift":null,
	"source_group":{
		"group_name":"GaiaAlerts",
		"groupid":"24"
	},
	"sourceid":"2",
	"spectra":[],
	"type":null
}