{
	"dec":"-04:20:16.33",
	"discmagfilter":{
		"family":"SkyMapper",
		"id":"60",
		"name":"g-SM"
	},
	"discoverer":null,
	"discovererid":"36338",
	"discoverydate":"2017-02-26 15:15:50",
	"discoverymag":"19.65",
	"end_prop_period":null,
	"host_redshift":null,
	"hostname":null,
	"internal_name":"SMT17cml",
	"isTNS_AT":"1",
	"name":"2017cja",
	"name_prefix":"AT",
	"object_type":{
		"id":null,
		"name":null
	},
	"objname":"2017cja",
	"public":"1",
	"ra":"10:54:04.46",
	"redshift":null,
	"source_group":{
		"group_name":"SkyMapper",
		"groupid":"5"
	},
	"sourceid":"2",
	"spectra":[],
	"type":null
}