{
	"dec":"+61:27:08.93",
	"discmagfilter":{
		"family":"Gaia",
		"id":"75",
		"name":"G"
	},
	"discoverer":null,
	"discovererid":"35587",
	"discoverydate":"2017-04-30 00:46:04",
	"discoverymag":"18.67",
	"end_prop_period":null,
	"host_redshift":null,
	"hostname":null,
	"internal_name":"Gaia17bdc",
	"isTNS_AT":"1",
	"name":"2017dpu",
	"name_prefix":"SN",
	"object_type":{
		"id":"10",
		"name":"SN II"
	},
	"objname":"2017dpu",
	"public":"1",
	"ra":"17:03:14.58",
	"redshift":"0.018",
	"source_group":{
		"group_name":"GaiaAlerts",
		"groupid":"24"
	},
	"sourceid":"2",
	"spectra":[
		{
			"asciifile":"https://wis-tns.weizmann.ac.il/system/files/uploaded/ASAS-SN/tns_2017dpu_2017-05-03_23-16-25_LT_SPRAT_ASAS-SN.dat",
			"assoc_groups":[
				{
					"id":"3",
					"name":"ASAS-SN"
				}
			],
			"end_prop_period":null,
			"exptime":"1800",
			"fitsfile":"",
			"instrument":{
				"id":"156",
				"name":"SPRAT"
			},
			"jd":2457877.4697338,
			"obsdate":"2017-05-03 23:16:25",
			"observer":"David Bersier",
			"public":"1",
			"reducer":"David Bersier",
			"remarks":"",
			"source_group":{
				"id":"3",
				"name":"ASAS-SN"
			},
			"telescope":{
				"id":"70",
				"name":"LT"
			}
		}
	],
	"type":"10"
}