{"end_prop_period": null, "discoverydate": "2017-01-04 09:01:26", "ra": "06:31:29.64", "dec": "+47:39:07.92", "hostname": null, "name": null, "public": "1", "isTNS_AT": "1", "discovererid": "35588", "objname": "2017aei", "type": null, "redshift": null, "internal_name": "PS17amf", "discoverymag": "19.94", "discmagfilter": "23", "spectra": [], "name_prefix": "AT", "host_redshift": null, "object_type": {"id": null, "name": null}, "source_group": {"group_name": "Pan-STARRS1", "groupid": "4"}, "discoverer": null, "sourceid": "2"}