{"objname": "2017yb", "ra": "02:53:24.40", "redshift": null, "hostname": null, "host_redshift": null, "isTNS_AT": "1", "discoverydate": "2017-01-24 06:54:43", "discoverymag": "18.62", "discmagfilter": "71", "public": "1", "end_prop_period": null, "sourceid": "2", "discovererid": "35595", "name_prefix": "AT", "type": null, "name": null, "discoverer": null, "internal_name": "ATLAS17ard", "spectra": [], "dec": "+15:46:05.61", "object_type": {"name": null, "id": null}, "source_group": {"groupid": "18", "group_name": "ATLAS"}}