{
	"dec":"+07:14:31.97",
	"discmagfilter":{
		"family":"PS1",
		"id":"26",
		"name":"w"
	},
	"discoverer":null,
	"discovererid":"35588",
	"discoverydate":"2017-12-29 14:34:04",
	"discoverymag":"21.25",
	"end_prop_period":null,
	"host_redshift":null,
	"hostname":null,
	"internal_name":"PS17gae",
	"isTNS_AT":"1",
	"name":"2017jtj",
	"name_prefix":"AT",
	"object_type":{
		"id":null,
		"name":null
	},
	"objname":"2017jtj",
	"public":"1",
	"ra":"11:23:42.79",
	"redshift":null,
	"source_group":{
		"group_name":"Pan-STARRS1",
		"groupid":"4"
	},
	"sourceid":"2",
	"spectra":[],
	"type":null
}