{"dec": "-02:20:36.69", "discmagfilter": "71", "discoverer": null, "discovererid": "35595", "discoverydate": "2017-02-24 12:10:04", "discoverymag": "18.86", "end_prop_period": null, "host_redshift": null, "hostname": null, "internal_name": "ATLAS17bjp", "isTNS_AT": "1", "name": "SN Ia", "name_prefix": "SN", "object_type": {"id": "3", "name": null}, "objname": "2017bxg", "public": "1", "ra": "10:40:34.73", "redshift": "0.04", "source_group": {"group_name": "ATLAS", "groupid": "18"}, "sourceid": "2", "spectra": [{"obsdate": "2017-03-08 07:42:41", "telescope": {"name": "ESO-NTT", "id": "30"}, "assoc_groups": [{"name": "PESSTO", "id": "1"}], "reducer": "F. Taddia, J. Sollerman, C. Fremling", "instrument": {"name": "EFOSC2-NTT", "id": "31"}, "observer": "C. Barbarino, A. Nyholm", "asciifile": "https://wis-tns.weizmann.ac.il/system/files/uploaded//tns_2017bxg_2017-03-08_07-42-41_ESO-NTT_EFOSC2-NTT.asci", "remarks": "", "exptime": "300", "jd": 2457820, "end_prop_period": null, "public": "1", "source_group": {"name": "PESSTO", "id": "1"}, "fitsfile": "https://wis-tns.weizmann.ac.il/system/files/uploaded//tns_2017bxg_2017-03-08_07-42-41_ESO-NTT_EFOSC2-NTT.fits"}], "type": "3"}