{
	"dec":"-33:58:01.29",
	"discmagfilter":{
		"family":"Johnson",
		"id":"12",
		"name":"V"
	},
	"discoverer":"Stanek",
	"discovererid":"82",
	"discoverydate":"2017-05-01 06:28:48",
	"discoverymag":"15.7",
	"end_prop_period":null,
	"host_redshift":"0.012465",
	"hostname":"IC 4296",
	"internal_name":"ASASSN-17fr",
	"isTNS_AT":"1",
	"name":"2017dps",
	"name_prefix":"SN",
	"object_type":{
		"id":"3",
		"name":"SN Ia"
	},
	"objname":"2017dps",
	"public":"1",
	"ra":"13:36:40.04",
	"redshift":"0.012",
	"source_group":{
		"group_name":"ASAS-SN",
		"groupid":"3"
	},
	"sourceid":"1",
	"spectra":[
		{
			"asciifile":"https://wis-tns.weizmann.ac.il/system/files/uploaded/NUTS/tns_2017dps_2017-05-02.99_NOT_ALFOSC_NUTS.dat",
			"assoc_groups":[
				{
					"id":"28",
					"name":"NUTS"
				}
			],
			"end_prop_period":null,
			"exptime":null,
			"fitsfile":"https://wis-tns.weizmann.ac.il/system/files/uploaded/NUTS/tns_2017dps_2017-05-02.99_NOT_ALFOSC_NUTS.fits",
			"instrument":{
				"id":"41",
				"name":"ALFOSC"
			},
			"jd":2457876.49,
			"obsdate":"2017-05-02 23:45:36",
			"observer":"J. Telting",
			"public":"1",
			"reducer":"N. Elias-Rosa",
			"remarks":"",
			"source_group":{
				"id":"28",
				"name":"NUTS"
			},
			"telescope":{
				"id":"12",
				"name":"NOT"
			}
		}
	],
	"type":"3"
}