{
	"dec":"+04:56:00.70",
	"discmagfilter":{
		"family":"Sloan",
		"id":"23",
		"name":"i"
	},
	"discoverer":null,
	"discovererid":"35588",
	"discoverydate":"2017-10-11 09:57:36",
	"discoverymag":"20.57",
	"end_prop_period":null,
	"host_redshift":null,
	"hostname":null,
	"internal_name":"PS17etc",
	"isTNS_AT":"1",
	"name":"2017hku",
	"name_prefix":"AT",
	"object_type":{
		"id":null,
		"name":null
	},
	"objname":"2017hku",
	"public":"1",
	"ra":"01:43:39.93",
	"redshift":null,
	"source_group":{
		"group_name":"Pan-STARRS1",
		"groupid":"4"
	},
	"sourceid":"2",
	"spectra":[],
	"type":null
}