{
	"dec":"-24:30:47.30",
	"discmagfilter":{
		"family":"Gaia",
		"id":"75",
		"name":"G"
	},
	"discoverer":null,
	"discovererid":"35587",
	"discoverydate":"2017-12-27 09:37:26",
	"discoverymag":"17.6",
	"end_prop_period":null,
	"host_redshift":null,
	"hostname":null,
	"internal_name":"Gaia17dku",
	"isTNS_AT":"1",
	"name":"2017jgf",
	"name_prefix":"SN",
	"object_type":{
		"id":"104",
		"name":"SN Ia-91T-like"
	},
	"objname":"2017jgf",
	"public":"1",
	"ra":"13:01:44.69",
	"redshift":"0.046",
	"source_group":{
		"group_name":"GaiaAlerts",
		"groupid":"24"
	},
	"sourceid":"2",
	"spectra":[
		{
			"asciifile":"https://wis-tns.weizmann.ac.il/system/files/uploaded/ePESSTO/tns_2017jgf_2018-01-06_06-51-41_ESO-NTT_EFOSC2-NTT_ePESSTO.asci",
			"assoc_groups":[
				{
					"id":"37",
					"name":"ePESSTO"
				}
			],
			"end_prop_period":null,
			"exptime":"300",
			"fitsfile":"https://wis-tns.weizmann.ac.il/system/files/uploaded/ePESSTO/tns_2017jgf_2018-01-06_06-51-41_ESO-NTT_EFOSC2-NTT_ePESSTO.fits",
			"instrument":{
				"id":"31",
				"name":"EFOSC2-NTT"
			},
			"jd":2458124.7858912,
			"obsdate":"2018-01-06 06:51:41",
			"observer":"M. Berton, F. Bufano",
			"public":"1",
			"reducer":"A. Floers, S. Taubenberger, C. Vogl",
			"remarks":"",
			"source_group":{
				"id":"37",
				"name":"ePESSTO"
			},
			"telescope":{
				"id":"30",
				"name":"ESO-NTT"
			}
		}
	],
	"type":"104"
}