{
	"dec":"-11:31:13.39",
	"discmagfilter":{
		"family":"ATLAS",
		"id":"71",
		"name":"cyan"
	},
	"discoverer":null,
	"discovererid":"35595",
	"discoverydate":"2017-08-21 12:38:52",
	"discoverymag":"19.18",
	"end_prop_period":null,
	"host_redshift":null,
	"hostname":null,
	"internal_name":"ATLAS17kht",
	"isTNS_AT":"1",
	"name":"2017goz",
	"name_prefix":"SN",
	"object_type":{
		"id":"3",
		"name":"SN Ia"
	},
	"objname":"2017goz",
	"public":"1",
	"ra":"23:19:14.77",
	"redshift":"0.07",
	"source_group":{
		"group_name":"ATLAS",
		"groupid":"18"
	},
	"sourceid":"2",
	"spectra":[
		{
			"asciifile":"https://wis-tns.weizmann.ac.il/system/files/uploaded/ePESSTO/tns_2017goz_2017-09-11_04-46-21_ESO-NTT_EFOSC2-NTT_ePESSTO.asci",
			"assoc_groups":[
				{
					"id":"37",
					"name":"ePESSTO"
				}
			],
			"end_prop_period":null,
			"exptime":"600",
			"fitsfile":"https://wis-tns.weizmann.ac.il/system/files/uploaded/ePESSTO/tns_2017goz_2017-09-11_04-46-21_ESO-NTT_EFOSC2-NTT_ePESSTO.fits",
			"instrument":{
				"id":"31",
				"name":"EFOSC2-NTT"
			},
			"jd":2458007.6988542,
			"obsdate":"2017-09-11 04:46:21",
			"observer":"Gromadzki,Rybicki",
			"public":"1",
			"reducer":"Fraser,Callis",
			"remarks":"",
			"source_group":{
				"id":"37",
				"name":"ePESSTO"
			},
			"telescope":{
				"id":"30",
				"name":"ESO-NTT"
			}
		}
	],
	"type":"3"
}