{"objname": "2017nu", "ra": "19:31:55.19", "redshift": null, "hostname": null, "host_redshift": null, "isTNS_AT": "1", "discoverydate": "2017-01-21 16:49:26", "discoverymag": "18.51", "discmagfilter": "75", "public": "1", "end_prop_period": null, "sourceid": "2", "discovererid": "35587", "name_prefix": "AT", "type": null, "name": null, "discoverer": null, "internal_name": "Gaia17afm", "spectra": [], "dec": "+30:56:04.16", "object_type": {"name": null, "id": null}, "source_group": {"groupid": "24", "group_name": "GaiaAlerts"}}