{
	"dec":"+55:53:11.63",
	"discmagfilter":{
		"family":"ATLAS",
		"id":"71",
		"name":"cyan"
	},
	"discoverer":null,
	"discovererid":"35595",
	"discoverydate":"2018-07-13 08:28:19",
	"discoverymag":"19.25",
	"end_prop_period":null,
	"host_redshift":null,
	"hostname":null,
	"internal_name":"ATLAS18sdy",
	"isTNS_AT":"1",
	"name":"2018dxu",
	"name_prefix":"SN",
	"object_type":{
		"id":"3",
		"name":"SN Ia"
	},
	"objname":"2018dxu",
	"public":"1",
	"ra":"14:30:09.92",
	"redshift":"0.108",
	"source_group":{
		"group_name":"ATLAS",
		"groupid":"18"
	},
	"sourceid":"2",
	"spectra":[],
	"type":"3"
}