{
	"dec":"-38:57:38.34",
	"discmagfilter":{
		"family":"Sloan",
		"id":"21",
		"name":"g"
	},
	"discoverer":"Stanek",
	"discovererid":"82",
	"discoverydate":"2018-11-18 06:28:48",
	"discoverymag":"17.5",
	"end_prop_period":null,
	"host_redshift":"0.041229",
	"hostname":"LCRS B041846.9-390434",
	"internal_name":"ASASSN-18zz",
	"isTNS_AT":"1",
	"name":"2018ioa",
	"name_prefix":"SN",
	"object_type":{
		"id":"3",
		"name":"SN Ia"
	},
	"objname":"2018ioa",
	"public":"1",
	"ra":"04:20:32.146",
	"redshift":"0.041229",
	"source_group":{
		"group_name":"ASAS-SN",
		"groupid":"3"
	},
	"sourceid":"1",
	"spectra":[
		{
			"asciifile":"https://wis-tns.weizmann.ac.il/system/files/uploaded/ASAS-SN/tns_2018ioa_2018-11-23.03_SALT_RSS_ASAS-SN.txt",
			"assoc_groups":[
				{
					"id":"3",
					"name":"ASAS-SN"
				}
			],
			"end_prop_period":null,
			"exptime":null,
			"fitsfile":"https://wis-tns.weizmann.ac.il/system/files/uploaded/ASAS-SN/tns_2018ioa_2018-11-23.03_SALT_RSS_ASAS-SN.fits",
			"instrument":{
				"id":"117",
				"name":"RSS"
			},
			"jd":2458445.53,
			"obsdate":"2018-11-23 00:43:12",
			"observer":"D. A. H. Buckley, M. Gromadzki",
			"public":"1",
			"reducer":"M. Gromadzki",
			"remarks":"",
			"source_group":{
				"id":"3",
				"name":"ASAS-SN"
			},
			"telescope":{
				"id":"82",
				"name":"SALT"
			}
		}
	],
	"type":"3"
}