{
	"dec":"-28:45:49.18",
	"discmagfilter":{
		"family":"Johnson",
		"id":"12",
		"name":"V"
	},
	"discoverer":"Stanek",
	"discovererid":"82",
	"discoverydate":"2018-09-14 08:38:24",
	"discoverymag":"15.2",
	"end_prop_period":null,
	"host_redshift":"0.007595",
	"hostname":"ESO 427- G 022",
	"internal_name":"ASASSN-18vm",
	"isTNS_AT":"1",
	"name":"2018ghb",
	"name_prefix":"SN",
	"object_type":{
		"id":"3",
		"name":"SN Ia"
	},
	"objname":"2018ghb",
	"public":"1",
	"ra":"06:58:27.60",
	"redshift":"0.005",
	"source_group":{
		"group_name":"ASAS-SN",
		"groupid":"3"
	},
	"sourceid":"1",
	"spectra":[
		{
			"asciifile":"https://wis-tns.weizmann.ac.il/system/files/uploaded/ePESSTO/tns_2018ghb_2018-09-15_09-43-14_ESO-NTT_EFOSC2-NTT_ePESSTO.asci",
			"assoc_groups":[
				{
					"id":"37",
					"name":"ePESSTO"
				}
			],
			"end_prop_period":null,
			"exptime":"180",
			"fitsfile":"https://wis-tns.weizmann.ac.il/system/files/uploaded/ePESSTO/tns_2018ghb_2018-09-15_09-43-14_ESO-NTT_EFOSC2-NTT_ePESSTO.fits",
			"instrument":{
				"id":"31",
				"name":"EFOSC2-NTT"
			},
			"jd":2458376.9050231,
			"obsdate":"2018-09-15 09:43:14",
			"observer":"T. Wevers, M. Gromadzki",
			"public":"1",
			"reducer":"J. Lyman",
			"remarks":"",
			"source_group":{
				"id":"37",
				"name":"ePESSTO"
			},
			"telescope":{
				"id":"30",
				"name":"ESO-NTT"
			}
		}
	],
	"type":"3"
}