{
	"dec":"+12:56:08.38",
	"discmagfilter":{
		"family":"Gaia",
		"id":"75",
		"name":"G"
	},
	"discoverer":null,
	"discovererid":"35587",
	"discoverydate":"2018-12-08 20:32:38",
	"discoverymag":"18.61",
	"end_prop_period":null,
	"host_redshift":null,
	"hostname":null,
	"internal_name":"Gaia18dtd",
	"isTNS_AT":"1",
	"name":"2018jqs",
	"name_prefix":"AT",
	"object_type":{
		"id":null,
		"name":null
	},
	"objname":"2018jqs",
	"public":"1",
	"ra":"19:48:03.160",
	"redshift":null,
	"source_group":{
		"group_name":"GaiaAlerts",
		"groupid":"24"
	},
	"sourceid":"2",
	"spectra":[],
	"type":null
}