{
	"dec":"+21:40:45.75",
	"decdeg":21.6793763,
	"discmagfilter":{
		"family":"ZTF",
		"id":111,
		"name":"r"
	},
	"discoverer":null,
	"discovererid":66140,
	"discovery_data_source":{
		"group_name":"ZTF",
		"groupid":48
	},
	"discoverydate":"2019-09-21 09:37:30",
	"discoverymag":20.1351,
	"end_prop_period":null,
	"host_redshift":0.267,
	"hostname":"SDSS J011608.54+214050.2",
	"internal_name":"ZTF19abzyblu",
	"internal_names":"ZTF19abzyblu",
	"isTNS_AT":1,
	"name":"2019qnh",
	"name_prefix":"AT",
	"object_type":{
		"id":null,
		"name":null
	},
	"objname":"2019qnh",
	"public":1,
	"ra":"01:16:08.669",
	"radeg":19.0361217,
	"redshift":null,
	"reporting_group":{
		"group_name":"ALeRCE",
		"groupid":74
	},
	"sourceid":2,
	"spectra":[],
	"type":null
}