{
	"dec":"+13:33:50.65",
	"decdeg":13.564069,
	"discmagfilter":{
		"family":"Gaia",
		"id":75,
		"name":"G"
	},
	"discoverer":"Lundquist",
	"discovererid":901,
	"discoverydate":"2019-04-28 03:09:35",
	"discoverymag":18.4,
	"end_prop_period":null,
	"host_redshift":null,
	"hostname":null,
	"internal_name":"",
	"isTNS_AT":1,
	"name":"2019ehj",
	"name_prefix":"AT",
	"object_type":{
		"id":null,
		"name":null
	},
	"objname":"2019ehj",
	"public":1,
	"ra":"08:20:04.510",
	"radeg":125.018792,
	"redshift":null,
	"source_group":{
		"group_name":"None",
		"groupid":0
	},
	"sourceid":1,
	"spectra":[],
	"type":null
}