{
	"dec":"+45:29:20.65",
	"decdeg":45.48907,
	"discmagfilter":{
		"family":"ZTF",
		"id":110,
		"name":"g"
	},
	"discoverer":null,
	"discovererid":49023,
	"discoverydate":"2019-09-21 07:48:55",
	"discoverymag":19.32,
	"end_prop_period":null,
	"host_redshift":null,
	"hostname":null,
	"internal_name":"ZTF19abzplvm",
	"internal_names":"ZTF19abzplvm",
	"isTNS_AT":1,
	"name":"2019qlx",
	"name_prefix":"SN",
	"object_type":{
		"id":3,
		"name":"SN Ia"
	},
	"objname":"2019qlx",
	"public":1,
	"ra":"23:59:00.452",
	"radeg":359.7518817,
	"redshift":0.103,
	"source_group":{
		"group_name":"ZTF",
		"groupid":48
	},
	"sourceid":2,
	"spectra":[
		{
			"asciifile":"https://wis-tns.weizmann.ac.il/system/files/uploaded/ZTF/tns_2019qlx_2019-10-01_08-10-25_P60_SEDM_ZTF.ascii",
			"assoc_groups":[
				{
					"id":48,
					"name":"ZTF"
				}
			],
			"end_prop_period":null,
			"exptime":2250,
			"fitsfile":null,
			"instrument":{
				"id":149,
				"name":"SEDM"
			},
			"jd":2458757.8405671,
			"obsdate":"2019-10-01 08:10:25",
			"observer":"SEDmRobot",
			"public":1,
			"reducer":"auto",
			"remarks":"",
			"source_group":{
				"id":48,
				"name":"ZTF"
			},
			"telescope":{
				"id":2,
				"name":"P60"
			}
		}
	],
	"type":3
}