{
	"dec":"-03:35:55.39",
	"decdeg":-3.59871906275,
	"discmagfilter":{
		"family":"PS1",
		"id":26,
		"name":"w"
	},
	"discoverer":null,
	"discovererid":35588,
	"discoverydate":"2019-05-01 06:08:38",
	"discoverymag":21.91,
	"end_prop_period":null,
	"host_redshift":null,
	"hostname":null,
	"internal_name":"PS19bog",
	"isTNS_AT":1,
	"name":"2019itg",
	"name_prefix":"AT",
	"object_type":{
		"id":null,
		"name":null
	},
	"objname":"2019itg",
	"public":1,
	"ra":"10:17:03.887",
	"radeg":154.266196548,
	"redshift":null,
	"source_group":{
		"group_name":"Pan-STARRS1",
		"groupid":4
	},
	"sourceid":2,
	"spectra":[],
	"type":null
}