{
	"dec":"+33:20:45.63",
	"decdeg":33.3460082,
	"discmagfilter":{
		"family":"ZTF",
		"id":111,
		"name":"r"
	},
	"discoverer":null,
	"discovererid":59228,
	"discoverydate":"2019-04-20 08:06:24",
	"discoverymag":18.46,
	"end_prop_period":null,
	"host_redshift":null,
	"hostname":null,
	"internal_name":"ZTF19aapbjcl",
	"isTNS_AT":1,
	"name":"2019dqk",
	"name_prefix":"AT",
	"object_type":{
		"id":null,
		"name":null
	},
	"objname":"2019dqk",
	"public":1,
	"ra":"18:23:50.197",
	"radeg":275.9591538,
	"redshift":null,
	"source_group":{
		"group_name":"ZTF",
		"groupid":48
	},
	"sourceid":2,
	"spectra":[],
	"type":null
}