{
	"dec":"+02:44:48.05",
	"decdeg":2.74668169852,
	"discmagfilter":{
		"family":"PS1",
		"id":26,
		"name":"w"
	},
	"discoverer":null,
	"discovererid":35588,
	"discoverydate":"2019-07-03 07:49:26",
	"discoverymag":21.98,
	"end_prop_period":null,
	"host_redshift":null,
	"hostname":null,
	"internal_name":"PS19dll",
	"isTNS_AT":1,
	"name":"2019koa",
	"name_prefix":"AT",
	"object_type":{
		"id":null,
		"name":null
	},
	"objname":"2019koa",
	"public":1,
	"ra":"14:48:32.609",
	"radeg":222.135872286,
	"redshift":null,
	"source_group":{
		"group_name":"Pan-STARRS1",
		"groupid":4
	},
	"sourceid":2,
	"spectra":[],
	"type":null
}