{
	"dec":"+00:00:00.00",
	"decdeg":-9.451039,
	"discmagfilter":{
		"family":"Gaia",
		"id":75,
		"name":"G"
	},
	"discoverer":null,
	"discovererid":35587,
	"discoverydate":"2019-04-05 21:02:52",
	"discoverymag":18.66,
	"end_prop_period":null,
	"host_redshift":null,
	"hostname":null,
	"internal_name":"Gaia19bfu",
	"isTNS_AT":1,
	"name":"2019cwp",
	"name_prefix":"AT",
	"object_type":{
		"id":null,
		"name":null
	},
	"objname":"2019cwp",
	"public":1,
	"ra":"18:06:56.840",
	"radeg":271.736833,
	"redshift":null,
	"source_group":{
		"group_name":"GaiaAlerts",
		"groupid":24
	},
	"sourceid":2,
	"spectra":[],
	"type":null
}