{
	"dec":"+10:33:01.20",
	"decdeg":10.5503331,
	"discmagfilter":{
		"family":"ZTF",
		"id":111,
		"name":"r"
	},
	"discoverer":null,
	"discovererid":59228,
	"discoverydate":"2019-06-10 11:04:28",
	"discoverymag":18.22,
	"end_prop_period":null,
	"host_redshift":null,
	"hostname":null,
	"internal_name":"ZTF19aayrosj",
	"isTNS_AT":1,
	"name":"2019hrb",
	"name_prefix":"SN",
	"object_type":{
		"id":10,
		"name":"SN II"
	},
	"objname":"2019hrb",
	"public":1,
	"ra":"20:54:12.083",
	"radeg":313.5503465,
	"redshift":0.015064,
	"source_group":{
		"group_name":"ZTF",
		"groupid":48
	},
	"sourceid":2,
	"spectra":[
		{
			"asciifile":"https://wis-tns.weizmann.ac.il/system/files/uploaded/ZTF/tns_2019hrb_2019-06-18_07-56-57_P60_SEDM_ZTF.ascii",
			"assoc_groups":[
				{
					"id":48,
					"name":"ZTF"
				}
			],
			"end_prop_period":null,
			"exptime":2250,
			"fitsfile":"",
			"instrument":{
				"id":149,
				"name":"SEDM"
			},
			"jd":2458652.8312153,
			"obsdate":"2019-06-18 07:56:57",
			"observer":"SEDmRobot",
			"public":1,
			"reducer":"auto",
			"remarks":"",
			"source_group":{
				"id":48,
				"name":"ZTF"
			},
			"telescope":{
				"id":2,
				"name":"P60"
			}
		}
	],
	"type":10
}