{
	"dec":"-51:32:09.60",
	"decdeg":-51.536,
	"decdeg_err":0,
	"discmagfilter":{
		"family":"Sloan",
		"id":21,
		"name":"g"
	},
	"discoverer":"J. Brimacombe, K. Z. Stanek, for the ASAS-SN team",
	"discoverer_internal_name":"ASASSN-20ls",
	"discovery_data_source":{
		"group_name":"ASAS-SN",
		"groupid":3
	},
	"discoverydate":"2020-09-15 23:45:36.000",
	"discoverymag":17,
	"end_prop_period":null,
	"host_redshift":0.011201,
	"hostname":"ESO 194- G 021",
	"internal_names":"ASASSN-20ls, Gaia20eqc",
	"name_prefix":"SN",
	"object_type":{
		"id":3,
		"name":"SN Ia"
	},
	"objid":66600,
	"objname":"2020tld",
	"public":1,
	"ra":"00:29:41.590",
	"radeg":7.423292,
	"radeg_err":0,
	"redshift":0.011201,
	"reporter":"Krzysztof Stanek",
	"reporterid":82,
	"reporting_group":{
		"group_name":"ASAS-SN",
		"groupid":3
	},
	"source":"user",
	"spectra":[
		{
			"asciifile":"https://wis-tns.weizmann.ac.il/system/files/uploaded/Global%20SN%20Project/tns_2020tld_2020-09-17_10-27-24_FTS_FLOYDS-S_Global_SN_Project.ascii",
			"assoc_groups":[
				{
					"id":38,
					"name":"Global SN Project"
				}
			],
			"end_prop_period":null,
			"exptime":2700,
			"fitsfile":"https://wis-tns.weizmann.ac.il/system/files/uploaded/Global%20SN%20Project/tns_2020tld_2020-09-17_10-27-24_FTS_FLOYDS-S_Global_SN_Project.fits",
			"instrument":{
				"id":125,
				"name":"FLOYDS-S"
			},
			"jd":2459109.9356944,
			"obsdate":"2020-09-17 10:27:24",
			"observer":"Las Cumbres Observatory",
			"public":1,
			"reducer":"Jamison Burke",
			"remarks":"",
			"source_group":{
				"id":38,
				"name":"Global SN Project"
			},
			"telescope":{
				"id":75,
				"name":"FTS"
			}
		}
	]
}