{
	"dec":"+44:17:46.62",
	"decdeg":44.296284,
	"discmagfilter":{
		"family":"ZTF",
		"id":110,
		"name":"g"
	},
	"discoverer":null,
	"discovererid":66140,
	"discovery_data_source":{
		"group_name":"ZTF",
		"groupid":48
	},
	"discoverydate":"2020-06-13 05:27:52.001",
	"discoverymag":20.0325,
	"end_prop_period":null,
	"host_redshift":0.160894,
	"hostname":"WISEA J110444.09+441746.2",
	"internal_name":"ZTF18aajhgwn",
	"internal_names":"ZTF18aajhgwn",
	"isTNS_AT":1,
	"name":"2020mnd",
	"name_prefix":"AT",
	"object_type":{
		"id":null,
		"name":null
	},
	"objname":"2020mnd",
	"public":1,
	"ra":"11:04:44.045",
	"radeg":166.1835211,
	"redshift":null,
	"reporting_group":{
		"group_name":"ALeRCE",
		"groupid":74
	},
	"sourceid":2,
	"spectra":[],
	"type":null
}