{
	"dec":"-11:56:02.05",
	"decdeg":-11.93390154,
	"decdeg_err":0,
	"discmagfilter":{
		"family":"ZTF",
		"id":110,
		"name":"g"
	},
	"discoverer":"F. Forster, F.E. Bauer, A. Munoz-Arancibia, L. Hernandez-Garcia, G. Pignata, L. Galbany, G. Pignata, E. Camacho, J. Silva-Farfan, A. Mourao, J. Arredondo, G. Cabrera-Vives, R. Carrasco-Davis, P.A. Estevez, P. Huijse, E. Reyes, I. Reyes, P. Sanchez-Saez, C. Valenzuela, E. Castillo, D. Ruz-Mieres, D. Rodriguez-Mancini, M. Catelan, S. Eyheramendy, M.J. Graham on behalf of the ALeRCE broker",
	"discoverer_internal_name":"ZTF20acppsay",
	"discovery_data_source":{
		"group_name":"ZTF",
		"groupid":48
	},
	"discoverydate":"2020-11-12 04:08:29.003",
	"discoverymag":19.6274,
	"end_prop_period":null,
	"host_redshift":null,
	"hostname":"WISEA J231240.50-115602.4",
	"internal_names":"ZTF20acppsay, PS20lhm, ATLAS20bftd",
	"name_prefix":"SN",
	"object_type":{
		"id":3,
		"name":"SN Ia"
	},
	"objid":70828,
	"objname":"2020zpf",
	"public":1,
	"ra":"23:12:40.484",
	"radeg":348.168683303,
	"radeg_err":0,
	"redshift":0.1,
	"reporter":"ALeRCE",
	"reporterid":66140,
	"reporting_group":{
		"group_name":"ALeRCE",
		"groupid":74
	},
	"source":"bot",
	"spectra":[
		{
			"asciifile":"https://www.wis-tns.org/system/files/uploaded/ePESSTO%2B/tns_2020zpf_2020-11-17_02-38-25_ESO-NTT_EFOSC2-NTT_ePESSTO%2B.asci",
			"assoc_groups":[
				{
					"id":63,
					"name":"ePESSTO+"
				}
			],
			"end_prop_period":null,
			"exptime":900,
			"fitsfile":"https://www.wis-tns.org/system/files/uploaded/ePESSTO%2B/tns_2020zpf_2020-11-17_02-38-25_ESO-NTT_EFOSC2-NTT_ePESSTO%2B.fits",
			"instrument":{
				"id":31,
				"name":"EFOSC2-NTT"
			},
			"jd":2459170.6100116,
			"obsdate":"2020-11-17 02:38:25",
			"observer":"N Ihanec, M. Gromadzki",
			"public":1,
			"reducer":"T. Wevers",
			"remarks":"",
			"source_group":{
				"id":63,
				"name":"ePESSTO+"
			},
			"telescope":{
				"id":30,
				"name":"ESO-NTT"
			}
		}
	]
}