{
	"dec":"+86:40:34.36",
	"decdeg":86.676211,
	"decdeg_err":0,
	"discmagfilter":{
		"family":"ZTF",
		"id":111,
		"name":"r"
	},
	"discoverer":"J. Nordin, V. Brinnel, M. Giomi, J. van Santen (HU Berlin), A. Gal-Yam, O. Yaron, S. Schulze (Weizmann) on behalf of ZTF",
	"discoverer_internal_name":"ZTF20abjonjs",
	"discovery_data_source":{
		"group_name":"ZTF",
		"groupid":48
	},
	"discoverydate":"2020-07-03 08:45:53.280",
	"discoverymag":19.58,
	"end_prop_period":null,
	"host_redshift":null,
	"hostname":null,
	"internal_names":"ZTF20abjonjs, ATLAS20saz, Gaia20dfq",
	"name_prefix":"SN",
	"object_type":{
		"id":10,
		"name":"SN II"
	},
	"objid":62667,
	"objname":"2020nyb",
	"public":1,
	"ra":"01:59:08.140",
	"radeg":29.783917,
	"radeg_err":0,
	"redshift":0.015527,
	"reporter":"ZTF_AMPEL_NEW",
	"reporterid":49023,
	"reporting_group":{
		"group_name":"ZTF",
		"groupid":48
	},
	"source":"bot",
	"spectra":[
		{
			"asciifile":"https://wis-tns.weizmann.ac.il/system/files/uploaded/ZTF/tns_2020nyb_2020-07-10_08-28-53_LT_SPRAT_ZTF.ascii",
			"assoc_groups":[
				{
					"id":48,
					"name":"ZTF"
				}
			],
			"end_prop_period":null,
			"exptime":null,
			"fitsfile":"",
			"instrument":{
				"id":156,
				"name":"SPRAT"
			},
			"jd":2459040.8533912,
			"obsdate":"2020-07-10 08:28:53",
			"observer":"LTRobot",
			"public":1,
			"reducer":"K. Taggart",
			"remarks":"",
			"source_group":{
				"id":48,
				"name":"ZTF"
			},
			"telescope":{
				"id":70,
				"name":"LT"
			}
		}
	]
}