{
	"dec":"-41:16:12.46",
	"decdeg":-41.2701266667,
	"decdeg_err":0,
	"discmagfilter":{
		"family":"ATLAS",
		"id":72,
		"name":"orange"
	},
	"discoverer":"J. Tonry, L. Denneau, A. Heinze, H. Weiland (IfA, University of Hawaii), B. Stalder (LSST), A. Rest (STScI), C. Stubbs (Harvard University), K. W. Smith, S. J. Smartt, D. R. Young, S. Srivastav, O. McBrien, M. Fulton, J. Gillanders (Queen's University Belfast), T.-W. Chen (MPE), D. E. Wright (University of Minnesota), J. Anderson (ESO)",
	"discoverer_internal_name":"ATLAS20bgfg",
	"discovery_data_source":{
		"group_name":"ATLAS",
		"groupid":18
	},
	"discoverydate":"2020-11-28 05:57:07.200",
	"discoverymag":18.405,
	"end_prop_period":null,
	"host_redshift":null,
	"hostname":null,
	"internal_names":"ATLAS20bgfg",
	"name_prefix":"AT",
	"object_type":{
		"id":null,
		"name":null
	},
	"objid":71894,
	"objname":"2020abct",
	"public":1,
	"ra":"23:15:38.466",
	"radeg":348.910273333,
	"radeg_err":0,
	"redshift":null,
	"reporter":"ATLAS_Bot1",
	"reporterid":35595,
	"reporting_group":{
		"group_name":"ATLAS",
		"groupid":18
	},
	"source":"bot",
	"spectra":[]
}