{
	"dec":"-24:46:09.64",
	"decdeg":-24.769344475,
	"decdeg_err":0.00027777777777778,
	"discmagfilter":{
		"family":"ZTF",
		"id":110,
		"name":"g"
	},
	"discoverer":"F. Forster, F.E. Bauer, A. Munoz-Arancibia, L. Hernandez-Garcia, G. Pignata, L. Galbany, G. Pignata, E. Camacho, J. Silva-Farfan, A. Mourao, J. Arredondo, G. Cabrera-Vives, R. Carrasco-Davis, P.A. Estevez, P. Huijse, E. Reyes, I. Reyes, P. Sanchez-Saez, C. Valenzuela, E. Castillo, D. Ruz-Mieres, D. Rodriguez-Mancini, M. Catelan, S. Eyheramendy, M.J. Graham on behalf of the ALeRCE broker",
	"discoverer_internal_name":"ZTF20aclftuo",
	"discovery_data_source":{
		"group_name":"ZTF",
		"groupid":48
	},
	"discoverydate":"2020-10-19 11:02:01.000",
	"discoverymag":20.3938,
	"end_prop_period":null,
	"host_redshift":0.04391,
	"hostname":"ESO 488- G 034",
	"internal_names":"ZTF20aclftuo, ATLAS20benf",
	"name_prefix":"SN",
	"object_type":{
		"id":10,
		"name":"SN II"
	},
	"objid":69345,
	"objname":"2020xlo",
	"public":1,
	"ra":"05:49:27.577",
	"radeg":87.364905675,
	"radeg_err":0.00027777777777778,
	"redshift":0.04391,
	"reporter":"ALeRCE",
	"reporterid":66140,
	"reporting_group":{
		"group_name":"ALeRCE",
		"groupid":74
	},
	"source":"bot",
	"spectra":[
		{
			"asciifile":"https://wis-tns.weizmann.ac.il/system/files/uploaded/adH0cc/tns_2020xlo_2020-10-24_07-16-34_VLT-UT1_FORS2_adH0cc.asci",
			"assoc_groups":[
				{
					"id":79,
					"name":"adH0cc"
				}
			],
			"end_prop_period":null,
			"exptime":900,
			"fitsfile":"https://wis-tns.weizmann.ac.il/system/files/uploaded/adH0cc/tns_2020xlo_2020-10-24_07-16-34_VLT-UT1_FORS2_adH0cc.fits",
			"instrument":{
				"id":7,
				"name":"FORS2"
			},
			"jd":2459146.8031713,
			"obsdate":"2020-10-24 07:16:34",
			"observer":"service",
			"public":1,
			"reducer":"S. Taubenberger",
			"remarks":"Quick-reduction spectrum, telluric correction applied.",
			"source_group":{
				"id":79,
				"name":"adH0cc"
			},
			"telescope":{
				"id":20,
				"name":"VLT-UT1"
			}
		}
	]
}