{
	"dec":"-04:08:46.14",
	"decdeg":-4.1461486961,
	"discmagfilter":{
		"family":"ZTF",
		"id":110,
		"name":"g"
	},
	"discoverer":null,
	"discovererid":66140,
	"discovery_data_source":{
		"group_name":"ZTF",
		"groupid":48
	},
	"discoverydate":"2020-05-27 10:07:24.004",
	"discoverymag":20.3872,
	"end_prop_period":null,
	"host_redshift":0.153,
	"hostname":"SDSS J213718.35-040846.8",
	"internal_name":"ZTF20abchxtq",
	"internal_names":"ZTF20abchxtq, PS20dzm",
	"isTNS_AT":1,
	"name":"2020lfs",
	"name_prefix":"AT",
	"object_type":{
		"id":null,
		"name":null
	},
	"objname":"2020lfs",
	"public":1,
	"ra":"21:37:18.055",
	"radeg":324.325229792,
	"redshift":null,
	"reporting_group":{
		"group_name":"ALeRCE",
		"groupid":74
	},
	"sourceid":2,
	"spectra":[],
	"type":null
}