{
	"dec":"+23:40:32.77",
	"decdeg":23.675769,
	"decdeg_err":0,
	"discmagfilter":{
		"family":"ATLAS",
		"id":72,
		"name":"orange"
	},
	"discoverer":"J. Tonry, L. Denneau, A. Heinze, H. Weiland, H. Flewelling (IfA, University of Hawaii), B. Stalder (LSST), A. Rest (STScI), C. Stubbs (Harvard University), K. W. Smith, S. J. Smartt, D. R. Young, S. Srivastav, O. McBrien, D. O'Neill, P. Clark, M. Fulton, J. Gillanders, M. Dobson (Queen's University Belfast), T.-W. Chen (MPE), D. E. Wright (University of Minnesota), J. Anderson (ESO), A. Townsend (University of Manchester)",
	"discoverer_internal_name":"ATLAS20sli",
	"discovery_data_source":{
		"group_name":"ATLAS",
		"groupid":18
	},
	"discoverydate":"2020-07-11 06:43:12.000",
	"discoverymag":18.644,
	"end_prop_period":null,
	"host_redshift":null,
	"hostname":null,
	"internal_names":"ATLAS20sli, Gaia20dmc",
	"name_prefix":"AT",
	"object_type":{
		"id":null,
		"name":null
	},
	"objid":63080,
	"objname":"2020ont",
	"public":1,
	"ra":"12:12:10.680",
	"radeg":183.0445,
	"radeg_err":0,
	"redshift":null,
	"reporter":"ATLAS_Bot1",
	"reporterid":35595,
	"reporting_group":{
		"group_name":"ATLAS",
		"groupid":18
	},
	"source":"bot",
	"spectra":[]
}