{
	"dec":"+51:30:02.35",
	"decdeg":51.5006540875,
	"decdeg_err":1.3571057208164e-05,
	"discmagfilter":{
		"family":"ZTF",
		"id":111,
		"name":"r"
	},
	"discoverer":"F. Forster, F.E. Bauer, G. Pignata, A. Munoz-Arancibia, L. Hernandez-Garcia, L. Galbany, G. Pignata, E. Camacho, J. Silva-Farfan, A. Mourao, J. Arredondo, G. Cabrera-Vives, R. Carrasco-Davis, P.A. Estevez, P. Huijse, E. Reyes, I. Reyes, P. Sanchez-Saez, C. Valenzuela, E. Castillo, D. Ruz-Mieres, D. Rodriguez-Mancini, M. Catelan, S. Eyheramendy, M.J. Graham on behalf of the ALeRCE broker",
	"discoverer_internal_name":"ZTF20acvkjrm",
	"discovery_data_source":{
		"group_name":"ZTF",
		"groupid":48
	},
	"discoverydate":"2020-12-02 12:47:42.000",
	"discoverymag":20.1103,
	"end_prop_period":null,
	"host_redshift":0.090698,
	"hostname":"WISEA J123604.86+513001.4",
	"internal_names":"ZTF20acvkjrm, ATLAS20bgzb",
	"name_prefix":"SN",
	"object_type":{
		"id":3,
		"name":"SN Ia"
	},
	"objid":72416,
	"objname":"2020abun",
	"public":1,
	"ra":"12:36:05.861",
	"radeg":189.0244203625,
	"radeg_err":2.7631184263759e-05,
	"redshift":0.090698,
	"reporter":"ALeRCE",
	"reporterid":66140,
	"reporting_group":{
		"group_name":"ALeRCE",
		"groupid":74
	},
	"source":"bot",
	"spectra":[
		{
			"asciifile":"https://www.wis-tns.org/system/files/uploaded/ZTF/tns_2020abun_2020-12-20_12-58-19.195388_P60_SEDM_ZTF.ascii",
			"assoc_groups":[
				{
					"id":48,
					"name":"ZTF"
				}
			],
			"end_prop_period":null,
			"exptime":2700,
			"fitsfile":"",
			"instrument":{
				"id":149,
				"name":"SEDM"
			},
			"jd":2459204.0404977,
			"obsdate":"2020-12-20 12:58:19",
			"observer":"SEDmRobot",
			"public":1,
			"reducer":"auto",
			"remarks":"",
			"source_group":{
				"id":48,
				"name":"ZTF"
			},
			"telescope":{
				"id":2,
				"name":"P60"
			}
		}
	]
}