{
	"dec":"+08:55:17.10",
	"decdeg":8.92141780846,
	"decdeg_err":0,
	"discmagfilter":{
		"family":"ZTF",
		"id":110,
		"name":"g"
	},
	"discoverer":"F. Forster, F.E. Bauer, A. Munoz-Arancibia, L. Hernandez-Garcia, G. Pignata, L. Galbany, G. Pignata, E. Camacho, J. Silva-Farfan, A. Mourao, J. Arredondo, G. Cabrera-Vives, R. Carrasco-Davis, P.A. Estevez, P. Huijse, E. Reyes, I. Reyes, P. Sanchez-Saez, C. Valenzuela, E. Castillo, D. Ruz-Mieres, D. Rodriguez-Mancini, M. Catelan, S. Eyheramendy, M.J. Graham on behalf of the ALeRCE broker",
	"discoverer_internal_name":"ZTF20acpjvzv",
	"discovery_data_source":{
		"group_name":"ZTF",
		"groupid":48
	},
	"discoverydate":"2020-11-11 05:04:56.004",
	"discoverymag":19.948,
	"end_prop_period":null,
	"host_redshift":0.346,
	"hostname":"SDSS J234401.69+085516.1",
	"internal_names":"ZTF20acpjvzv, PS20lhz",
	"name_prefix":"AT",
	"object_type":{
		"id":null,
		"name":null
	},
	"objid":70582,
	"objname":"2020zft",
	"public":1,
	"ra":"23:44:01.680",
	"radeg":356.007001145,
	"radeg_err":0,
	"redshift":null,
	"reporter":"ALeRCE",
	"reporterid":66140,
	"reporting_group":{
		"group_name":"ALeRCE",
		"groupid":74
	},
	"source":"bot",
	"spectra":[]
}