{
	"dec":"+69:58:33.96",
	"decdeg":69.9760998,
	"discmagfilter":{
		"family":"ZTF",
		"id":111,
		"name":"r"
	},
	"discoverer":null,
	"discovererid":49023,
	"discovery_data_source":{
		"group_name":"ZTF",
		"groupid":48
	},
	"discoverydate":"2020-01-26 06:18:02",
	"discoverymag":18.21,
	"end_prop_period":null,
	"host_redshift":null,
	"hostname":null,
	"internal_name":"ZTF18acpkfvb",
	"internal_names":"ZTF18acpkfvb",
	"isTNS_AT":1,
	"name":"2020axn",
	"name_prefix":"AT",
	"object_type":{
		"id":null,
		"name":null
	},
	"objname":"2020axn",
	"public":1,
	"ra":"11:23:38.549",
	"radeg":170.91061943333,
	"redshift":null,
	"reporting_group":{
		"group_name":"ZTF",
		"groupid":48
	},
	"sourceid":2,
	"spectra":[],
	"type":null
}