{
	"dec":"+84:22:51.46",
	"decdeg":84.380961,
	"decdeg_err":0,
	"discmagfilter":{
		"family":"ZTF",
		"id":110,
		"name":"g"
	},
	"discoverer":"A. Munoz-Arancibia, A. Mourao, F. Forster, F.E. Bauer, L. Hernandez-Garcia, G. Pignata, L. Galbany, E. Camacho, J. Silva-Farfan, J. Arredondo, G. Cabrera-Vives, R. Carrasco-Davis, P.A. Estevez, P. Huijse, E. Reyes, I. Reyes, P. Sanchez-Saez, C. Valenzuela, E. Castillo, D. Ruz-Mieres, D. Rodriguez-Mancini, M. Catelan, S. Eyheramendy, M.J. Graham on behalf of the ALeRCE broker",
	"discoverer_internal_name":"ZTF21aadoizf",
	"discovery_data_source":{
		"group_name":"ZTF",
		"groupid":48
	},
	"discoverydate":"2021-01-12 07:49:34.997",
	"discoverymag":18.7548,
	"end_prop_period":null,
	"host_redshift":0.007412,
	"hostname":"NGC 2268",
	"internal_names":"ZTF21aadoizf, Gaia21ahu",
	"name_prefix":"SN",
	"object_type":{
		"id":10,
		"name":"SN II"
	},
	"objid":75206,
	"objname":"2021aai",
	"public":1,
	"ra":"07:14:26.860",
	"radeg":108.611917,
	"radeg_err":0,
	"redshift":0.007412,
	"reporter":"ALeRCE",
	"reporterid":66140,
	"reporting_group":{
		"group_name":"ALeRCE",
		"groupid":74
	},
	"source":"bot",
	"spectra":[
		{
			"asciifile":"https://www.wis-tns.org/system/files/uploaded/ZTF/tns_2021aai_2021-01-13_02-23-58.439358_P60_SEDM_ZTF.ascii",
			"assoc_groups":[
				{
					"id":48,
					"name":"ZTF"
				}
			],
			"end_prop_period":null,
			"exptime":2700,
			"fitsfile":"",
			"instrument":{
				"id":149,
				"name":"SEDM"
			},
			"jd":2459227.5999769,
			"obsdate":"2021-01-13 02:23:58",
			"observer":"SEDmRobot",
			"public":1,
			"reducer":"auto",
			"remarks":"",
			"source_group":{
				"id":48,
				"name":"ZTF"
			},
			"telescope":{
				"id":2,
				"name":"P60"
			}
		}
	]
}